./.gitignore
./CLAUDE.md
./LICENSE
./PKG-INFO
./README.md
./mixtaper.py
./pyproject.toml
./run_tests.py
./uv.lock
./.github/workflows/ci-cd.yml
./mixtaper/__init__.py
./mixtaper/artwork_generator.py
./mixtaper/audio_analyzer.py
./mixtaper/cli.py
./mixtaper/config.py
./mixtaper/metadata_manager.py
./mixtaper/mixtape_optimizer.py
./mixtaper/musicbrainz_client.py
./mixtaper/tui.py
./tests/__init__.py
./tests/test_config.py
./tests/test_metadata_manager.py
./tests/test_mixtape_optimizer.py
mixtaper-0.1.0.dist-info/METADATA
mixtaper-0.1.0.dist-info/WHEEL
mixtaper-0.1.0.dist-info/entry_points.txt
mixtaper-0.1.0.dist-info/licenses/LICENSE
mixtaper-0.1.0.dist-info/RECORD
