Metadata-Version: 2.4
Name: mixtaper
Version: 0.1.0
Summary: AI-powered mixtape creator that analyzes audio files and crafts perfect track sequences
Project-URL: Homepage, https://github.com/ido50/mixtaper
Project-URL: Repository, https://github.com/ido50/mixtaper
Project-URL: Issues, https://github.com/ido50/mixtaper/issues
Author: Mixtaper Contributors
License: Apache-2.0
License-File: LICENSE
Keywords: ai,audio,cli,flow,mixtape,music,ordering
Classifier: Development Status :: 4 - Beta
Classifier: Environment :: Console
Classifier: Intended Audience :: End Users/Desktop
Classifier: License :: OSI Approved :: MIT License
Classifier: Operating System :: OS Independent
Classifier: Programming Language :: Python :: 3
Classifier: Programming Language :: Python :: 3.8
Classifier: Programming Language :: Python :: 3.9
Classifier: Programming Language :: Python :: 3.10
Classifier: Programming Language :: Python :: 3.11
Classifier: Programming Language :: Python :: 3.12
Classifier: Topic :: Multimedia :: Sound/Audio :: Analysis
Classifier: Topic :: Utilities
Requires-Python: >=3.8
Requires-Dist: librosa>=0.10.1
Requires-Dist: mutagen>=1.47.0
Requires-Dist: numpy>=1.24.0
Requires-Dist: openai>=1.0.0
Requires-Dist: requests>=2.31.0
Requires-Dist: rich>=13.7.0
Requires-Dist: scipy>=1.10.0
Provides-Extra: dev
Requires-Dist: pytest-cov>=4.0.0; extra == 'dev'
Requires-Dist: pytest>=7.0.0; extra == 'dev'
